abide/__init__.py
abide-0.0.1.dist-info/METADATA
abide-0.0.1.dist-info/WHEEL
abide-0.0.1.dist-info/entry_points.txt
abide-0.0.1.dist-info/top_level.txt
abide-0.0.1.dist-info/RECORD
